{
  "basics": {
    "name": "Shyam Charan Kesavamoorthi",
    "label": "",
    "image": "",
    "email": "shyamcharan.nitt@gmail.com",
    "phone": "+91 9600380810",
    "url": "https://inclinedtaco.github.io/",
    "summary": "An undergraduate researcher in robot learning.",
    "location": {
      "address": "",
      "postalCode": "",
      "city": "",
      "countryCode": "",
      "region": ""
    },
    "profiles": [
      {
        "network": "X",
        "username": "thisizshyam",
        "url": "https://x.com/thisizshyam"
      },
      {
        "network": "LinkedIn",
        "username": "Shyam Charan",
        "url": "https://www.linkedin.com/in/shyamcharan/"
      },
      {
        "network": "Email",
        "username": "",
        "url": "shyamcharan.nitt@gmail.com"
      }
    ]
  },
  "work": [
    {
      "name": "Multi-Agent Robotic Motion Laboratory, NUS",
      "position": "Undergraduate Researcher",
      "startDate": "2025-05",
      "endDate": "Present",
      "summary": "Developing and evaluating a general loco-manipulation policy by combining imitation learning and reinforcement learning techniques.",
      "highlights": [
        "Loco-manipulation",
        "Imitation Learning",
        "Reinforcement Learning",
        "IsaacLab",
        "MuJoCo"
      ]
    },
    {
      "name": "DACAS Lab, IISc Bangalore",
      "position": "Quadrotor Research Intern",
      "startDate": "2025-05",
      "endDate": "2025-07",
      "summary": "Developed conditional diffusion models for multi-step uncertainty prediction in quadrotor residual dynamics and analyzed tradeoffs for real-time robotics deployment.",
      "highlights": [
        "Conditional Diffusion Models",
        "Uncertainty Prediction",
        "Quadrotor Dynamics",
        "Generative Models",
        "Real-time Robotics"
      ]
    },
    {
      "name": "Thryv Mobility",
      "position": "Embedded Systems Intern",
      "startDate": "2024-06",
      "endDate": "2024-07",
      "summary": "Designed and fabricated PCBs for power management, implemented I2C/SPI drivers for accelerometers, and developed embedded systems using ESP-IDF and BLE protocols.",
      "highlights": [
        "Embedded Systems",
        "PCB Design",
        "ESP-IDF",
        "BLE",
        "I2C/SPI Drivers"
      ]
    }
  ],
  "education": [
    {
      "institution": "National Institute of Technology Tiruchirappalli",
      "location": "Tiruchirappalli, India",
      "area": "Instrumentation and Control Engineering",
      "studyType": "Bachelor of Technology",
      "startDate": "2022",
      "endDate": "2026",
      "score": "",
      "courses": [
        "Robotics, Neural Networks and Fuzzy Logic, Control Systems"
      ]
    }
  ],
  "skills": [
    {
      "name": "Physics",
      "level": "Master",
      "icon": "fa-solid fa-hashtag",
      "keywords": [
        "Quantum Mechanics",
        "Quantum Computing",
        "Quantum Information",
        "Quantum Cryptography",
        "Quantum Communication",
        "Quantum Teleportation"
      ]
    }
  ],
  "languages": [
    {
      "language": "English",
      "fluency": "Fluent",
      "icon": ""
    },
    {
      "language": "Tamil",
      "fluency": "Native Speaker",
      "icon": ""
    }
  ],
  "interests": [
    {
      "name": "Physics",
      "icon": "fa-solid fa-tag",
      "keywords": [
        "Quantum Mechanics",
        "Quantum Computing",
        "Quantum Information",
        "Quantum Cryptography",
        "Quantum Communication",
        "Quantum Teleportation"
      ]
    }
  ]
}
